django_razorpay/__init__.py
django_razorpay/admin.py
django_razorpay/apps.py
django_razorpay/models.py
django_razorpay/tests.py
django_razorpay/urls.py
django_razorpay/utils.py
django_razorpay/views.py
django_razorpay/management/__init__.py
django_razorpay/management/commands/__init__.py
django_razorpay/management/commands/dj_razorpay_init.py
django_razorpay/migrations/0001_initial.py
django_razorpay/migrations/__init__.py
django_razorpay/static/django_razorpay/css/bootstrap-datepicker.min.css
django_razorpay/static/django_razorpay/css/bootstrap-select.min.css
django_razorpay/static/django_razorpay/css/bootstrap.min.css
django_razorpay/static/django_razorpay/css/bootstrap.min.css.map
django_razorpay/static/django_razorpay/js/bootstrap-datepicker.min.js
django_razorpay/static/django_razorpay/js/bootstrap-select.min.js
django_razorpay/static/django_razorpay/js/bootstrap.bundle.min.js
django_razorpay/static/django_razorpay/js/bootstrap.bundle.min.js.map
django_razorpay/static/django_razorpay/js/jquery.min.js
django_razorpay/templates/django_razorpay/adhoc_payment.html
django_razorpay/templates/django_razorpay/base.html
django_razorpay/templates/django_razorpay/checkout.html
django_razorpay/templates/django_razorpay/manual_transaction.html
django_razorpay/templates/django_razorpay/membership_fee.html
django_razorpay/templates/django_razorpay/payment_status.html
django_razorpay/templates/django_razorpay/transactions.html
django_razorpay/templates/django_razorpay/transactions_list.html
django_razorpay/templatetags/__init__.py
django_razorpay/templatetags/dj_razorpay.py
django_razorpay-1.1.2.dist-info/LICENSE
django_razorpay-1.1.2.dist-info/METADATA
django_razorpay-1.1.2.dist-info/WHEEL
django_razorpay-1.1.2.dist-info/top_level.txt
django_razorpay-1.1.2.dist-info/RECORD
